apd/aggregation/__init__.py
apd/aggregation/analysis.py
apd/aggregation/cli.py
apd/aggregation/collect.py
apd/aggregation/database.py
apd/aggregation/exceptions.py
apd/aggregation/py.typed
apd/aggregation/query.py
apd/aggregation/typing.py
apd/aggregation/utils.py
apd/aggregation/actions/__init__.py
apd/aggregation/actions/action.py
apd/aggregation/actions/base.py
apd/aggregation/actions/runner.py
apd/aggregation/actions/source.py
apd/aggregation/actions/trigger.py
apd/aggregation/alembic/env.py
apd/aggregation/alembic/versions/4b2df8a6e1ce_add_indexes_to_datapoints.py
apd/aggregation/alembic/versions/6962f8455a6d_add_daily_summary_view.py
apd/aggregation/alembic/versions/6d2eacd5da3f_create_sensor_values_table.py
apd/aggregation/alembic/versions/d8cdc709086b_add_deployment_table.py
apd/aggregation/alembic/versions/d8d4cf6a178f_add_deployment_id_to_datapoint.py
apd.aggregation-2.0.2.dist-info/LICENCE
apd.aggregation-2.0.2.dist-info/METADATA
apd.aggregation-2.0.2.dist-info/WHEEL
apd.aggregation-2.0.2.dist-info/entry_points.txt
apd.aggregation-2.0.2.dist-info/top_level.txt
apd.aggregation-2.0.2.dist-info/RECORD
