Metadata-Version: 2.1
Name: apd.aggregation
Version: 2.0.2
Summary: A programme that queries apd.sensor endpoints and aggregates their results.
Home-page: UNKNOWN
License: BSD
Platform: UNKNOWN
Classifier: Programming Language :: Python :: 3
Classifier: Programming Language :: Python :: 3.7
Classifier: Programming Language :: Python :: 3.8
Requires-Dist: sqlalchemy
Requires-Dist: aiohttp
Requires-Dist: pint
Requires-Dist: psycopg2
Requires-Dist: alembic
Requires-Dist: click
Requires-Dist: typing-extensions ; python_version < "3.8"
Provides-Extra: jupyter
Requires-Dist: ipywidgets ; extra == 'jupyter'
Requires-Dist: matplotlib ; extra == 'jupyter'
Provides-Extra: yappi
Requires-Dist: yappi ; extra == 'yappi'
